CHANGES.md
LICENSE
MANIFEST.in
README.rst
requirements-dev.txt
requirements.txt
setup.cfg
setup.py
mountebank/__init__.py
mountebank/imposter.py
mountebank/tests/__init__.py
mountebank/tests/test_mountebank.py
pymountebank.egg-info/PKG-INFO
pymountebank.egg-info/SOURCES.txt
pymountebank.egg-info/dependency_links.txt
pymountebank.egg-info/requires.txt
pymountebank.egg-info/top_level.txt