Metadata-Version: 1.1
Name: pymountebank
Version: 1.4.0
Summary: Mountebank wrapper for mocking HTTP APIs
Home-page: https://github.com/quid/pymountebank
Author: Quid Inc
Author-email: infrastructure@quid.com
License: BSD 3-Clause License
Platform: UNKNOWN
Classifier: Intended Audience :: Developers
Classifier: License :: OSI Approved :: BSD License
Classifier: Natural Language :: English
Classifier: Operating System :: OS Independent
Classifier: Programming Language :: Python :: 2
Classifier: Programming Language :: Python :: 2.6
Classifier: Programming Language :: Python :: 2.7
Classifier: Programming Language :: Python :: 3
Classifier: Programming Language :: Python :: 3.3
Classifier: Programming Language :: Python :: 3.4
Classifier: Programming Language :: Python
Classifier: Topic :: Software Development :: Libraries :: Python Modules
